cybereason/__init__.py
cybereason/_typing.py
cybereason/client.py
cybereason/exceptions.py
cybereason/incident_response.py
cybereason/malops.py
cybereason/py.typed
cybereason/rules.py
cybereason/sensors.py
cybereason/system.py
cybereason/threat_intel.py
cybereason/parse/__init__.py
cybereason/parse/cef.py
cybereason/parse/server.py
cybereason/utils/__init__.py
cybereason/utils/guid.py
cybereason-0.6.3.dist-info/LICENSE
cybereason-0.6.3.dist-info/METADATA
cybereason-0.6.3.dist-info/WHEEL
cybereason-0.6.3.dist-info/top_level.txt
cybereason-0.6.3.dist-info/RECORD
