Metadata-Version: 2.1
Name: cybereason
Version: 0.6.3
Summary: Async Cybereason API client
Home-page: https://github.com/forensic-security/cybereason#readme
Author: Nuno André
Author-email: mail@nunoand.re
License: BSD-3-Clause
Project-URL: Source, https://github.com/forensic-security/cybereason
Project-URL: Bug Tracker, https://github.com/forensic-security/cybereason/issues
Keywords: cybereason,cybersecurity,security,edr
Platform: any
Classifier: Development Status :: 4 - Beta
Classifier: Intended Audience :: Developers
Classifier: Intended Audience :: System Administrators
Classifier: Framework :: AsyncIO
Classifier: License :: OSI Approved :: BSD License
Classifier: Natural Language :: English
Classifier: Operating System :: OS Independent
Classifier: Programming Language :: Python
Classifier: Programming Language :: Python :: 3.8
Classifier: Programming Language :: Python :: 3.9
Classifier: Programming Language :: Python :: 3.10
Classifier: Programming Language :: Python :: 3.11
Classifier: Programming Language :: Python :: 3.12
Classifier: Topic :: Security
Classifier: Typing :: Typed
Requires-Python: >=3.8
License-File: LICENSE
Requires-Dist: httpx[http2] <0.28,>=0.26.0
Provides-Extra: dev
Requires-Dist: fqdn ; extra == 'dev'
Requires-Dist: idna ; extra == 'dev'
Requires-Dist: isoduration ; extra == 'dev'
Requires-Dist: jsonschema ; extra == 'dev'
Requires-Dist: mypy ; extra == 'dev'
Requires-Dist: pytest ; extra == 'dev'
Requires-Dist: pytest-asyncio ==0.21.2 ; extra == 'dev'
Requires-Dist: pytest-datafiles ; extra == 'dev'
Requires-Dist: pyyaml ; extra == 'dev'
Requires-Dist: rfc3339-validator ; extra == 'dev'
Requires-Dist: rfc3987 ; extra == 'dev'
Requires-Dist: ruff ; extra == 'dev'
Provides-Extra: docs
Requires-Dist: sphinx ; extra == 'docs'
Requires-Dist: sphinx-rtd-theme ; extra == 'docs'
Provides-Extra: socks
Requires-Dist: httpx-socks[asyncio] ; extra == 'socks'
Provides-Extra: zip
Requires-Dist: pyzipper ; extra == 'zip'
